README.txt
setup.py
docs/AUTHORS.txt
docs/CHANGES.txt
docs/LICENSE.GPL
docs/LICENSE.txt
p4a/__init__.py
p4a.plonevideo.egg-info/PKG-INFO
p4a.plonevideo.egg-info/SOURCES.txt
p4a.plonevideo.egg-info/dependency_links.txt
p4a.plonevideo.egg-info/entry_points.txt
p4a.plonevideo.egg-info/namespace_packages.txt
p4a.plonevideo.egg-info/not-zip-safe
p4a.plonevideo.egg-info/requires.txt
p4a.plonevideo.egg-info/top_level.txt
p4a/plonevideo/__init__.py
p4a/plonevideo/atct.py
p4a/plonevideo/configure.zcml
p4a/plonevideo/content.py
p4a/plonevideo/media.py
p4a/plonevideo/p4a-plonevideo.txt
p4a/plonevideo/plone-video-impl.txt
p4a/plonevideo/plone-video.txt
p4a/plonevideo/sitesetup.py
p4a/plonevideo/syndication.py
p4a/plonevideo/syndication.txt
p4a/plonevideo/syndication.zcml
p4a/plonevideo/Extensions/__init__.py
p4a/plonevideo/Extensions/install.py
p4a/plonevideo/atvideo/__init__.py
p4a/plonevideo/atvideo/atvideotests.py
p4a/plonevideo/atvideo/browser.py
p4a/plonevideo/atvideo/configure.zcml
p4a/plonevideo/atvideo/interfaces.py
p4a/plonevideo/atvideo/migrate-atvideo-configlet.pt
p4a/plonevideo/atvideo/migration.py
p4a/plonevideo/atvideo/migration.txt
p4a/plonevideo/browser/__init__.py
p4a/plonevideo/browser/configure.zcml
p4a/plonevideo/browser/video.py
p4a/plonevideo/tests/__init__.py
p4a/plonevideo/tests/test_functional.py
p4a/plonevideo/tests/test_unit.py