Metadata-Version: 1.0
Name: p4a.plonevideo
Version: 1.3
Summary: Plone4Artists video add-on for Plone
Home-page: http://plone.org/products/plone4artistsvideo
Author: Rocky Burt
Author-email: rocky@serverzen.com
License: GPL
Keywords: Plone4Artists iPod Quicktime video multimedia vodcast Flash flv
Platform: UNKNOWN
Classifier: Framework :: Zope2
Classifier: Framework :: Zope3
Classifier: Framework :: Plone
Classifier: Programming Language :: Python
Classifier: License :: OSI Approved :: GNU General Public License (GPL)
Classifier: Topic :: Software Development :: Libraries :: Python Modules
Classifier: Topic :: Multimedia :: Video
